okrager/__init__.py
okrager/crc.py
okrager/exceptions.py
okrager/injector.py
okrager/logger.py
okrager/mymc.py
okrager/stagers/bin/stage1.bin
okrager/stagers/bin/stage2.bin
okrager-0.1.0.data/scripts/okrager
okrager-0.1.0.dist-info/LICENSE.md
okrager-0.1.0.dist-info/METADATA
okrager-0.1.0.dist-info/WHEEL
okrager-0.1.0.dist-info/top_level.txt
okrager-0.1.0.dist-info/RECORD
