Metadata-Version: 2.1
Name: okrager
Version: 0.1.0
Summary: Command line tool to inject a PS2 ELF into an Okage Shadow King game save file
Home-page: https://github.com/McCaulay/okrager
Author: McCaulay Hudson
Author-email: mccaulayhudson@protonmail.com
Maintainer: McCaulay Hudson
License: MIT
Keywords: ps2 gamesave psu okage shadow king mast1c0re
Platform: Unix
Platform: Windows
Classifier: Development Status :: 4 - Beta
Classifier: Environment :: Console
Classifier: Intended Audience :: Science/Research
Classifier: License :: OSI Approved :: MIT License
Classifier: Programming Language :: Python :: 3
License-File: LICENSE.md
Requires-Dist: mymcplus (==3.0.5)
Requires-Dist: pypsu (==0.1.2)
